mdlinks/__init__.py
mdlinks/cli.py
mdlinks-0.1.0.dist-info/METADATA
mdlinks-0.1.0.dist-info/WHEEL
mdlinks-0.1.0.dist-info/entry_points.txt
mdlinks-0.1.0.dist-info/top_level.txt
mdlinks-0.1.0.dist-info/RECORD
