Metadata-Version: 2.4
Name: mdlinks
Version: 0.1.0
Summary: Generate Markdown links from a list of URLs
Requires-Python: >=3.12
Requires-Dist: click>=8.3.1
Requires-Dist: lxml>=6.0.2
Requires-Dist: requests>=2.32.5
